tmp/job_1/Noise_Filter.v
// Generator : SpinalHDL v1.6.1    git head : 3bf789d53b1b5a36974196e2d591342e15ddf28c
// Component : Noise_Filter

`timescale 1ns/1ps 

module Noise_Filter (
  input               data_in,
  output              data_out,
  input               clk,
  input               reset
);

  reg        [3:0]    data_delayed;
  reg                 temp;

  assign data_out = temp;
  always @(posedge clk or posedge reset) begin
    if(reset) begin
      data_delayed <= 4'b0000;
      temp <= data_in;
    end else begin
      data_delayed <= {data_delayed[2],{data_delayed[1],{data_delayed[0],data_in}}};
      temp <= ((((data_delayed[1] && data_delayed[2]) && data_delayed[3]) && (! temp)) || ((! (((! data_delayed[1]) && (! data_delayed[2])) && (! data_delayed[3]))) && temp));
    end
  end


endmodule

simWorkspace/Noise_Filter/test.vcd
$version Generated by VerilatedVcd $end
$date Mon Mar 07 13:38:21 2022
 $end
$timescale   1ns $end

 $scope module TOP $end
  $var wire  1 C clk $end
  $var wire  1 3 data_in $end
  $var wire  1 ; data_out $end
  $var wire  1 K reset $end
  $scope module Noise_Filter $end
   $var wire  1 C clk $end
   $var wire  4 # data_delayed [3:0] $end
   $var wire  1 3 data_in $end
   $var wire  1 ; data_out $end
   $var wire  1 K reset $end
   $var wire  1 + temp $end
  $upscope $end
 $upscope $end
$enddefinitions $end


#0
b0000 #
1+
13
1;
0C
1K
#160
0K
#170
b0001 #
0+
0;
1C
#175
0C
#180
b0011 #
1C
#185
0C
#190
b0111 #
1C
#195
0C
#200
b1111 #
1C
#205
0C
#210
1+
1;
1C
#215
0C
#220
1C
#225
0C
#230
1C
#235
0C
#240
1C
#245
0C
#250
1C
#255
0C
#260
1C
#265
0C
#270
03
1C
#275
0C
#280
b1110 #
13
1C
#285
0C
#290
b1101 #
1C
#295
0C
#300
b1011 #
1C
#305
0C
#310
b0111 #
03
1C
#315
0C
#320
b1110 #
1C
#325
0C
#330
b1100 #
1C
#335
0C
#340
b1000 #
13
1C
#345
0C
#350
b0001 #
1C
#355
0C
#360
b0011 #
0+
03
0;
1C
#365
0C
#370
b0110 #
1C
#375
0C
#380
b1100 #
13
1C
#385
0C
#390
b1001 #
1C
#395
0C
#400
b0011 #
1C
#405
0C
#410
b0111 #
1C
#415
0C
#420
b1111 #
03
1C
#425
0C
#430
b1110 #
1+
1;
1C
#435
0C
#440
b1100 #
1C
#445
0C
#450
b1000 #
1C
#455
0C
#460
b0000 #
1C
#465
0C
#470
0+
0;
1C
